apaya_logger/__init__.py
apaya_logger/logger.py
apaya_py_logger-1.0.9.dist-info/METADATA
apaya_py_logger-1.0.9.dist-info/WHEEL
apaya_py_logger-1.0.9.dist-info/top_level.txt
apaya_py_logger-1.0.9.dist-info/RECORD
